determine_docker_tags/__init__.py
determine_docker_tags-0.2.6.dist-info/LICENSE
determine_docker_tags-0.2.6.dist-info/METADATA
determine_docker_tags-0.2.6.dist-info/WHEEL
determine_docker_tags-0.2.6.dist-info/entry_points.txt
determine_docker_tags-0.2.6.dist-info/RECORD
