Metadata-Version: 2.1
Name: determine-docker-tags
Version: 0.2.6
Summary: A small program to determine docker image tags
Home-page: https://git.walbeck.it/walbeck-it/determine-docker-tags
Author: Magnus Walbeck
Author-email: magnus.walbeck@walbeck.it
Requires-Python: >=3.7,<4.0
Classifier: Programming Language :: Python :: 3
Classifier: Programming Language :: Python :: 3.7
Classifier: Programming Language :: Python :: 3.8
Classifier: Programming Language :: Python :: 3.9
Classifier: Programming Language :: Python :: 3.10
Classifier: Programming Language :: Python :: 3.11
Classifier: Programming Language :: Python :: 3.12
Classifier: Programming Language :: Python :: 3.13
Project-URL: Repository, https://git.walbeck.it/walbeck-it/determine-docker-tags
